{
  "storn": "STN001",
  "version": 1,
  "isReturnUser": "1",
  "doNotDisplayWelcomePage": "No",
  "agents": [
    {
      "agentReferenceNumber": "ARN001",
      "name": "Agent 1 Legal LLP",
      "agentId": "AGT001",
      "houseNumber": "11",
      "addressLine1": "Example Street 1",
      "addressLine2": "Westminster",
      "addressLine3": "London",
      "addressLine4": "United Kingdom",
      "postcode": "SW1A 01AA",
      "phone": "02079460001",
      "email": "contact.agent1@examplelaw.co.uk"
    },
    {
      "agentReferenceNumber": "ARN002",
      "name": "Agent 2 Legal LLP",
      "agentId": "AGT002",
      "houseNumber": "12",
      "addressLine1": "Example Street 2",
      "addressLine2": "Westminster",
      "addressLine3": "London",
      "addressLine4": "United Kingdom",
      "postcode": "SW1A 02AA",
      "phone": "02079460002",
      "email": "contact.agent2@examplelaw.co.uk"
    },
    {
      "agentReferenceNumber": "ARN003",
      "name": "Agent 3 Legal LLP",
      "agentId": "AGT003",
      "houseNumber": "13",
      "addressLine1": "Example Street 3",
      "addressLine2": "Westminster",
      "addressLine3": "London",
      "addressLine4": "United Kingdom",
      "postcode": "SW1A 03AA",
      "phone": "02079460003",
      "email": "contact.agent3@examplelaw.co.uk"
    },
    {
      "agentReferenceNumber": "ARN004",
      "name": "Agent 4 Legal LLP",
      "agentId": "AGT004",
      "houseNumber": "14",
      "addressLine1": "Example Street 4",
      "addressLine2": "Westminster",
      "addressLine3": "London",
      "addressLine4": "United Kingdom",
      "postcode": "SW1A 04AA",
      "phone": "02079460004",
      "email": "contact.agent4@examplelaw.co.uk"
    },
    {
      "agentReferenceNumber": "ARN005",
      "name": "Agent 5 Legal LLP",
      "agentId": "AGT005",
      "houseNumber": "15",
      "addressLine1": "Example Street 5",
      "addressLine2": "Westminster",
      "addressLine3": "London",
      "addressLine4": "United Kingdom",
      "postcode": "SW1A 05AA",
      "phone": "02079460005",
      "email": "contact.agent5@examplelaw.co.uk"
    },
    {
      "agentReferenceNumber": "ARN006",
      "name": "Agent 6 Legal LLP",
      "agentId": "AGT006",
      "houseNumber": "16",
      "addressLine1": "Example Street 6",
      "addressLine2": "Westminster",
      "addressLine3": "London",
      "addressLine4": "United Kingdom",
      "postcode": "SW1A 06AA",
      "phone": "02079460006",
      "email": "contact.agent6@examplelaw.co.uk"
    },
    {
      "agentReferenceNumber": "ARN007",
      "name": "Agent 7 Legal LLP",
      "agentId": "AGT007",
      "houseNumber": "17",
      "addressLine1": "Example Street 7",
      "addressLine2": "Westminster",
      "addressLine3": "London",
      "addressLine4": "United Kingdom",
      "postcode": "SW1A 07AA",
      "phone": "02079460007",
      "email": "contact.agent7@examplelaw.co.uk"
    },
    {
      "agentReferenceNumber": "ARN008",
      "name": "Agent 8 Legal LLP",
      "agentId": "AGT008",
      "houseNumber": "18",
      "addressLine1": "Example Street 8",
      "addressLine2": "Westminster",
      "addressLine3": "London",
      "addressLine4": "United Kingdom",
      "postcode": "SW1A 08AA",
      "phone": "02079460008",
      "email": "contact.agent8@examplelaw.co.uk"
    },
    {
      "agentReferenceNumber": "ARN009",
      "name": "Agent 9 Legal LLP",
      "agentId": "AGT009",
      "houseNumber": "19",
      "addressLine1": "Example Street 9",
      "addressLine2": "Westminster",
      "addressLine3": "London",
      "addressLine4": "United Kingdom",
      "postcode": "SW1A 09AA",
      "phone": "02079460009",
      "email": "contact.agent9@examplelaw.co.uk"
    },
    {
      "agentReferenceNumber": "ARN010",
      "name": "Agent 10 Legal LLP",
      "agentId": "AGT010",
      "houseNumber": "20",
      "addressLine1": "Example Street 10",
      "addressLine2": "Westminster",
      "addressLine3": "London",
      "addressLine4": "United Kingdom",
      "postcode": "SW1A 10AA",
      "phone": "02079460010",
      "email": "contact.agent10@examplelaw.co.uk"
    },
    {
      "agentReferenceNumber": "ARN011",
      "name": "Agent 11 Legal LLP",
      "agentId": "AGT011",
      "houseNumber": "21",
      "addressLine1": "Example Street 11",
      "addressLine2": "Westminster",
      "addressLine3": "London",
      "addressLine4": "United Kingdom",
      "postcode": "SW1A 11AA",
      "phone": "02079460011",
      "email": "contact.agent11@examplelaw.co.uk"
    },
    {
      "agentReferenceNumber": "ARN012",
      "name": "Agent 12 Legal LLP",
      "agentId": "AGT012",
      "houseNumber": "22",
      "addressLine1": "Example Street 12",
      "addressLine2": "Westminster",
      "addressLine3": "London",
      "addressLine4": "United Kingdom",
      "postcode": "SW1A 12AA",
      "phone": "02079460012",
      "email": "contact.agent12@examplelaw.co.uk"
    },
    {
      "agentReferenceNumber": "ARN013",
      "name": "Agent 13 Legal LLP",
      "agentId": "AGT013",
      "houseNumber": "23",
      "addressLine1": "Example Street 13",
      "addressLine2": "Westminster",
      "addressLine3": "London",
      "addressLine4": "United Kingdom",
      "postcode": "SW1A 13AA",
      "phone": "02079460013",
      "email": "contact.agent13@examplelaw.co.uk"
    },
    {
      "agentReferenceNumber": "ARN014",
      "name": "Agent 14 Legal LLP",
      "agentId": "AGT014",
      "houseNumber": "24",
      "addressLine1": "Example Street 14",
      "addressLine2": "Westminster",
      "addressLine3": "London",
      "addressLine4": "United Kingdom",
      "postcode": "SW1A 14AA",
      "phone": "02079460014",
      "email": "contact.agent14@examplelaw.co.uk"
    },
    {
      "agentReferenceNumber": "ARN015",
      "name": "Agent 15 Legal LLP",
      "agentId": "AGT015",
      "houseNumber": "25",
      "addressLine1": "Example Street 15",
      "addressLine2": "Westminster",
      "addressLine3": "London",
      "addressLine4": "United Kingdom",
      "postcode": "SW1A 15AA",
      "phone": "02079460015",
      "email": "contact.agent15@examplelaw.co.uk"
    },
    {
      "agentReferenceNumber": "ARN016",
      "name": "Agent 16 Legal LLP",
      "agentId": "AGT016",
      "houseNumber": "26",
      "addressLine1": "Example Street 16",
      "addressLine2": "Westminster",
      "addressLine3": "London",
      "addressLine4": "United Kingdom",
      "postcode": "SW1A 16AA",
      "phone": "02079460016",
      "email": "contact.agent16@examplelaw.co.uk"
    },
    {
      "agentReferenceNumber": "ARN017",
      "name": "Agent 17 Legal LLP",
      "agentId": "AGT017",
      "houseNumber": "27",
      "addressLine1": "Example Street 17",
      "addressLine2": "Westminster",
      "addressLine3": "London",
      "addressLine4": "United Kingdom",
      "postcode": "SW1A 17AA",
      "phone": "02079460017",
      "email": "contact.agent17@examplelaw.co.uk"
    },
    {
      "agentReferenceNumber": "ARN018",
      "name": "Agent 18 Legal LLP",
      "agentId": "AGT018",
      "houseNumber": "28",
      "addressLine1": "Example Street 18",
      "addressLine2": "Westminster",
      "addressLine3": "London",
      "addressLine4": "United Kingdom",
      "postcode": "SW1A 18AA",
      "phone": "02079460018",
      "email": "contact.agent18@examplelaw.co.uk"
    },
    {
      "agentReferenceNumber": "ARN019",
      "name": "Agent 19 Legal LLP",
      "agentId": "AGT019",
      "houseNumber": "29",
      "addressLine1": "Example Street 19",
      "addressLine2": "Westminster",
      "addressLine3": "London",
      "addressLine4": "United Kingdom",
      "postcode": "SW1A 19AA",
      "phone": "02079460019",
      "email": "contact.agent19@examplelaw.co.uk"
    },
    {
      "agentReferenceNumber": "ARN020",
      "name": "Agent 20 Legal LLP",
      "agentId": "AGT020",
      "houseNumber": "30",
      "addressLine1": "Example Street 20",
      "addressLine2": "Westminster",
      "addressLine3": "London",
      "addressLine4": "United Kingdom",
      "postcode": "SW1A 20AA",
      "phone": "02079460020",
      "email": "contact.agent20@examplelaw.co.uk"
    },
    {
      "agentReferenceNumber": "ARN021",
      "name": "Agent 21 Legal LLP",
      "agentId": "AGT021",
      "houseNumber": "31",
      "addressLine1": "Example Street 21",
      "addressLine2": "Westminster",
      "addressLine3": "London",
      "addressLine4": "United Kingdom",
      "postcode": "SW1A 21AA",
      "phone": "02079460021",
      "email": "contact.agent21@examplelaw.co.uk"
    },
    {
      "agentReferenceNumber": "ARN022",
      "name": "Agent 22 Legal LLP",
      "agentId": "AGT022",
      "houseNumber": "32",
      "addressLine1": "Example Street 22",
      "addressLine2": "Westminster",
      "addressLine3": "London",
      "addressLine4": "United Kingdom",
      "postcode": "SW1A 22AA",
      "phone": "02079460022",
      "email": "contact.agent22@examplelaw.co.uk"
    },
    {
      "agentReferenceNumber": "ARN023",
      "name": "Agent 23 Legal LLP",
      "agentId": "AGT023",
      "houseNumber": "33",
      "addressLine1": "Example Street 23",
      "addressLine2": "Westminster",
      "addressLine3": "London",
      "addressLine4": "United Kingdom",
      "postcode": "SW1A 23AA",
      "phone": "02079460023",
      "email": "contact.agent23@examplelaw.co.uk"
    },
    {
      "agentReferenceNumber": "ARN024",
      "name": "Agent 24 Legal LLP",
      "agentId": "AGT024",
      "houseNumber": "34",
      "addressLine1": "Example Street 24",
      "addressLine2": "Westminster",
      "addressLine3": "London",
      "addressLine4": "United Kingdom",
      "postcode": "SW1A 24AA",
      "phone": "02079460024",
      "email": "contact.agent24@examplelaw.co.uk"
    },
    {
      "agentReferenceNumber": "ARN025",
      "name": "Agent 25 Legal LLP",
      "agentId": "AGT025",
      "houseNumber": "35",
      "addressLine1": "Example Street 25",
      "addressLine2": "Westminster",
      "addressLine3": "London",
      "addressLine4": "United Kingdom",
      "postcode": "SW1A 25AA",
      "phone": "02079460025",
      "email": "contact.agent25@examplelaw.co.uk"
    }
  ]
}
